LICENSE.txt
README.md
setup.py
calendate/__init__.py
calendate/calendar_calc.py
calendate.egg-info/PKG-INFO
calendate.egg-info/SOURCES.txt
calendate.egg-info/dependency_links.txt
calendate.egg-info/top_level.txt